.binstar.yml
.coveragerc
.gitignore
.mailmap
.travis.yml
ANNOUNCE.rst
DISK_FORMAT_v1.rst
MANIFEST.in
README.rst
RELEASE_NOTES.rst
THANKS.rst
appveyor.yml
coveralls_after_test_succes.sh
cpuinfo.py
makefile
persistence.rst
requirements.txt
requirements_rtfd.txt
requirements_test.txt
setup.py
LICENSES/APPVEYOR-DEMO.txt
LICENSES/BCOLZ.txt
LICENSES/BLOSC.txt
LICENSES/FASTLZ.txt
LICENSES/LZ4.txt
LICENSES/NUMPY.txt
LICENSES/SNAPPY.txt
LICENSES/STDINT.txt
LICENSES/ZLIB.txt
bcolz/PythonHelper.h
bcolz/__init__.py
bcolz/arrayprint.py
bcolz/attrs.py
bcolz/carray_ext.c
bcolz/carray_ext.pxd
bcolz/carray_ext.pyx
bcolz/check_blosc_version.h
bcolz/chunked_eval.py
bcolz/ctable.py
bcolz/defaults.py
bcolz/definitions.pxd
bcolz/py2help.py
bcolz/py2help_tests.py
bcolz/toplevel.py
bcolz/utils.py
bcolz/version.py
bcolz.egg-info/PKG-INFO
bcolz.egg-info/SOURCES.txt
bcolz.egg-info/dependency_links.txt
bcolz.egg-info/requires.txt
bcolz.egg-info/top_level.txt
bcolz/tests/__init__.py
bcolz/tests/all.py
bcolz/tests/common.py
bcolz/tests/test_attrs.py
bcolz/tests/test_carray.py
bcolz/tests/test_carray_objects.py
bcolz/tests/test_ctable.py
bcolz/tests/test_ndcarray.py
bcolz/tests/test_queries.py
bench/arange.py
bench/column-iter.py
bench/concat.py
bench/ctable-query.py
bench/eval-profile.py
bench/eval.py
bench/eval_and_replace.py
bench/expression.py
bench/fill.py
bench/fromiter.py
bench/getitem.py
bench/iter.py
bench/iterator.py
bench/iterblocks.py
bench/large_carray.py
bench/multithreaded_copy.ipynb
bench/objpickles.py
bench/pandas-fromdataframe-strings.py
bench/pandas-fromdataframe.py
bench/pandas-todataframe.py
bench/pytables-fromhdf5.py
bench/pytables-tohdf5.py
bench/query.py
bench/run.sh
bench/serialization.py
bench/sum.py
bench/whereblocks.py
bench/zeros.py
bench/zlib-vs-cblosc-zlib.ipynb
bench_asv/README_asv.md
bench_asv/asv.conf.json
bench_asv/bench/__init__.py
bench_asv/bench/arange.py
bench_asv/bench/bench_helper.py
bench_asv/bench/column_iter.py
bench_asv/bench/concat.py
c-blosc/.editorconfig
c-blosc/.gitignore
c-blosc/.mailmap
c-blosc/.travis.yml
c-blosc/ANNOUNCE.rst
c-blosc/CMakeLists.txt
c-blosc/README.md
